{
  "data": [
    {
      "TeamID": 1610612742,
      "SEASON": "2025",
      "LeagueID": "00",
      "PLAYER": "John Poulakidas",
      "NICKNAME": "John",
      "PLAYER_SLUG": "john-poulakidas",
      "NUM": null,
      "POSITION": "G",
      "HEIGHT": "6-6",
      "WEIGHT": "205",
      "BIRTH_DATE": "APR 04, 2003",
      "AGE": 23.0,
      "EXP": "R",
      "SCHOOL": "Yale",
      "PLAYER_ID": 1642967,
      "HOW_ACQUIRED": "Signed on 02/28/26"
    },
    {
      "TeamID": 1610612742,
      "SEASON": "2025",
      "LeagueID": "00",
      "PLAYER": "Max Christie",
      "NICKNAME": "Max",
      "PLAYER_SLUG": "max-christie",
      "NUM": "00",
      "POSITION": "G",
      "HEIGHT": "6-5",
      "WEIGHT": "190",
      "BIRTH_DATE": "FEB 10, 2003",
      "AGE": 23.0,
      "EXP": "3",
      "SCHOOL": "Michigan State",
      "PLAYER_ID": 1631108,
      "HOW_ACQUIRED": "Traded from LAL on 02/02/25"
    },
    {
      "TeamID": 1610612742,
      "SEASON": "2025",
      "LeagueID": "00",
      "PLAYER": "Dereck Lively II",
      "NICKNAME": "Dereck",
      "PLAYER_SLUG": "dereck-lively-ii",
      "NUM": "2",
      "POSITION": "C",
      "HEIGHT": "7-1",
      "WEIGHT": "230",
      "BIRTH_DATE": "FEB 12, 2004",
      "AGE": 22.0,
      "EXP": "2",
      "SCHOOL": "Duke",
      "PLAYER_ID": 1641726,
      "HOW_ACQUIRED": "Draft Rights Traded from OKC on 07/06/23"
    },
    {
      "TeamID": 1610612742,
      "SEASON": "2025",
      "LeagueID": "00",
      "PLAYER": "Dwight Powell",
      "NICKNAME": "Dwight",
      "PLAYER_SLUG": "dwight-powell",
      "NUM": "7",
      "POSITION": "F-C",
      "HEIGHT": "6-10",
      "WEIGHT": "240",
      "BIRTH_DATE": "JUL 20, 1991",
      "AGE": 34.0,
      "EXP": "11",
      "SCHOOL": "Stanford",
      "PLAYER_ID": 203939,
      "HOW_ACQUIRED": "Traded from BOS on 12/18/14"
    },
    {
      "TeamID": 1610612742,
      "SEASON": "2025",
      "LeagueID": "00",
      "PLAYER": "AJ Johnson",
      "NICKNAME": "AJ",
      "PLAYER_SLUG": "aj-johnson",
      "NUM": "8",
      "POSITION": "G",
      "HEIGHT": "6-5",
      "WEIGHT": "160",
      "BIRTH_DATE": "DEC 01, 2004",
      "AGE": 21.0,
      "EXP": "1",
      "SCHOOL": "Illawarra",
      "PLAYER_ID": 1642358,
      "HOW_ACQUIRED": "Traded from WAS on 02/05/26"
    },
    {
      "TeamID": 1610612742,
      "SEASON": "2025",
      "LeagueID": "00",
      "PLAYER": "Ryan Nembhard",
      "NICKNAME": "Ryan",
      "PLAYER_SLUG": "ryan-nembhard",
      "NUM": "9",
      "POSITION": "G",
      "HEIGHT": "5-11",
      "WEIGHT": "180",
      "BIRTH_DATE": "MAR 10, 2003",
      "AGE": 23.0,
      "EXP": "R",
      "SCHOOL": "Gonzaga",
      "PLAYER_ID": 1642948,
      "HOW_ACQUIRED": "Signed on 07/03/25"
    },
    {
      "TeamID": 1610612742,
      "SEASON": "2025",
      "LeagueID": "00",
      "PLAYER": "Brandon Williams",
      "NICKNAME": "Brandon",
      "PLAYER_SLUG": "brandon-williams",
      "NUM": "10",
      "POSITION": "G",
      "HEIGHT": "6-1",
      "WEIGHT": "190",
      "BIRTH_DATE": "NOV 22, 1999",
      "AGE": 26.0,
      "EXP": "3",
      "SCHOOL": "Arizona",
      "PLAYER_ID": 1630314,
      "HOW_ACQUIRED": "Signed on 12/28/23"
    },
    {
      "TeamID": 1610612742,
      "SEASON": "2025",
      "LeagueID": "00",
      "PLAYER": "Kyrie Irving",
      "NICKNAME": "Kyrie",
      "PLAYER_SLUG": "kyrie-irving",
      "NUM": "11",
      "POSITION": "G",
      "HEIGHT": "6-2",
      "WEIGHT": "195",
      "BIRTH_DATE": "MAR 23, 1992",
      "AGE": 34.0,
      "EXP": "14",
      "SCHOOL": "Duke",
      "PLAYER_ID": 202681,
      "HOW_ACQUIRED": "Traded from BKN on 02/06/23"
    },
    {
      "TeamID": 1610612742,
      "SEASON": "2025",
      "LeagueID": "00",
      "PLAYER": "Naji Marshall",
      "NICKNAME": "Naji",
      "PLAYER_SLUG": "naji-marshall",
      "NUM": "13",
      "POSITION": "F",
      "HEIGHT": "6-6",
      "WEIGHT": "220",
      "BIRTH_DATE": "JAN 24, 1998",
      "AGE": 28.0,
      "EXP": "5",
      "SCHOOL": "Xavier",
      "PLAYER_ID": 1630230,
      "HOW_ACQUIRED": "Signed on 07/06/24"
    },
    {
      "TeamID": 1610612742,
      "SEASON": "2025",
      "LeagueID": "00",
      "PLAYER": "Caleb Martin",
      "NICKNAME": "Caleb",
      "PLAYER_SLUG": "caleb-martin",
      "NUM": "16",
      "POSITION": "F",
      "HEIGHT": "6-5",
      "WEIGHT": "205",
      "BIRTH_DATE": "SEP 28, 1995",
      "AGE": 30.0,
      "EXP": "6",
      "SCHOOL": "Nevada",
      "PLAYER_ID": 1628997,
      "HOW_ACQUIRED": "Traded from PHI on 02/04/25"
    },
    {
      "TeamID": 1610612742,
      "SEASON": "2025",
      "LeagueID": "00",
      "PLAYER": "Khris Middleton",
      "NICKNAME": "Khris",
      "PLAYER_SLUG": "khris-middleton",
      "NUM": "20",
      "POSITION": "F",
      "HEIGHT": "6-7",
      "WEIGHT": "222",
      "BIRTH_DATE": "AUG 12, 1991",
      "AGE": 34.0,
      "EXP": "13",
      "SCHOOL": "Texas A&M",
      "PLAYER_ID": 203114,
      "HOW_ACQUIRED": "Traded from WAS on 02/05/26"
    },
    {
      "TeamID": 1610612742,
      "SEASON": "2025",
      "LeagueID": "00",
      "PLAYER": "Daniel Gafford",
      "NICKNAME": "Daniel",
      "PLAYER_SLUG": "daniel-gafford",
      "NUM": "21",
      "POSITION": "F-C",
      "HEIGHT": "6-10",
      "WEIGHT": "265",
      "BIRTH_DATE": "OCT 01, 1998",
      "AGE": 27.0,
      "EXP": "6",
      "SCHOOL": "Arkansas",
      "PLAYER_ID": 1629655,
      "HOW_ACQUIRED": "Traded from WAS on 02/08/24"
    },
    {
      "TeamID": 1610612742,
      "SEASON": "2025",
      "LeagueID": "00",
      "PLAYER": "Tyler Smith",
      "NICKNAME": "Tyler",
      "PLAYER_SLUG": "tyler-smith",
      "NUM": "21",
      "POSITION": "F",
      "HEIGHT": "6-9",
      "WEIGHT": "224",
      "BIRTH_DATE": "NOV 02, 2004",
      "AGE": 21.0,
      "EXP": "1",
      "SCHOOL": "NBA G League Ignite",
      "PLAYER_ID": 1641890,
      "HOW_ACQUIRED": "Signed on 02/28/26"
    },
    {
      "TeamID": 1610612742,
      "SEASON": "2025",
      "LeagueID": "00",
      "PLAYER": "P.J. Washington",
      "NICKNAME": "P.J.",
      "PLAYER_SLUG": "pj-washington",
      "NUM": "25",
      "POSITION": "F",
      "HEIGHT": "6-7",
      "WEIGHT": "230",
      "BIRTH_DATE": "AUG 23, 1998",
      "AGE": 27.0,
      "EXP": "6",
      "SCHOOL": "Kentucky",
      "PLAYER_ID": 1629023,
      "HOW_ACQUIRED": "Traded from CHA on 02/08/24"
    },
    {
      "TeamID": 1610612742,
      "SEASON": "2025",
      "LeagueID": "00",
      "PLAYER": "Moussa Cisse",
      "NICKNAME": "Moussa",
      "PLAYER_SLUG": "moussa-cisse",
      "NUM": "30",
      "POSITION": "C",
      "HEIGHT": "6-11",
      "WEIGHT": "220",
      "BIRTH_DATE": "SEP 10, 2002",
      "AGE": 23.0,
      "EXP": "R",
      "SCHOOL": "Memphis",
      "PLAYER_ID": 1630619,
      "HOW_ACQUIRED": "Signed on 07/08/25"
    },
    {
      "TeamID": 1610612742,
      "SEASON": "2025",
      "LeagueID": "00",
      "PLAYER": "Klay Thompson",
      "NICKNAME": "Klay",
      "PLAYER_SLUG": "klay-thompson",
      "NUM": "31",
      "POSITION": "G",
      "HEIGHT": "6-5",
      "WEIGHT": "220",
      "BIRTH_DATE": "FEB 08, 1990",
      "AGE": 36.0,
      "EXP": "14",
      "SCHOOL": "Washington State",
      "PLAYER_ID": 202691,
      "HOW_ACQUIRED": "Traded from GSW on 07/06/24"
    },
    {
      "TeamID": 1610612742,
      "SEASON": "2025",
      "LeagueID": "00",
      "PLAYER": "Cooper Flagg",
      "NICKNAME": "Cooper",
      "PLAYER_SLUG": "cooper-flagg",
      "NUM": "32",
      "POSITION": "F",
      "HEIGHT": "6-9",
      "WEIGHT": "205",
      "BIRTH_DATE": "DEC 21, 2006",
      "AGE": 19.0,
      "EXP": "R",
      "SCHOOL": "Duke",
      "PLAYER_ID": 1642843,
      "HOW_ACQUIRED": "#1 Pick in 2025 Draft"
    },
    {
      "TeamID": 1610612742,
      "SEASON": "2025",
      "LeagueID": "00",
      "PLAYER": "Marvin Bagley III",
      "NICKNAME": "Marvin",
      "PLAYER_SLUG": "marvin-bagley-iii",
      "NUM": "35",
      "POSITION": "F",
      "HEIGHT": "6-10",
      "WEIGHT": "235",
      "BIRTH_DATE": "MAR 14, 1999",
      "AGE": 27.0,
      "EXP": "7",
      "SCHOOL": "Duke",
      "PLAYER_ID": 1628963,
      "HOW_ACQUIRED": "Traded from WAS on 02/05/26"
    }
  ],
  "cached_at": "2026-04-20T23:40:18.377582",
  "endpoint": "team_roster",
  "params": {
    "team_id": 1610612742,
    "season": "2025-26"
  }
}