{
  "data": [
    {
      "SEASON_ID": "22004",
      "Player_ID": 2544,
      "Game_ID": "0020401218",
      "GAME_DATE": "Apr 20, 2005",
      "MATCHUP": "CLE @ TOR",
      "WL": "W",
      "MIN": 48,
      "FGM": 10,
      "FGA": 23,
      "FG_PCT": 0.435,
      "FG3M": 2,
      "FG3A": 8,
      "FG3_PCT": 0.25,
      "FTM": 5,
      "FTA": 10,
      "FT_PCT": 0.5,
      "OREB": 2,
      "DREB": 12,
      "REB": 14,
      "AST": 14,
      "STL": 0,
      "BLK": 1,
      "TOV": 2,
      "PF": 1,
      "PTS": 27,
      "PLUS_MINUS": 9,
      "VIDEO_AVAILABLE": 0
    },
    {
      "SEASON_ID": "22004",
      "Player_ID": 2544,
      "Game_ID": "0020401209",
      "GAME_DATE": "Apr 19, 2005",
      "MATCHUP": "CLE vs. BOS",
      "WL": "W",
      "MIN": 47,
      "FGM": 13,
      "FGA": 27,
      "FG_PCT": 0.481,
      "FG3M": 2,
      "FG3A": 3,
      "FG3_PCT": 0.667,
      "FTM": 4,
      "FTA": 5,
      "FT_PCT": 0.8,
      "OREB": 1,
      "DREB": 7,
      "REB": 8,
      "AST": 6,
      "STL": 5,
      "BLK": 0,
      "TOV": 3,
      "PF": 3,
      "PTS": 32,
      "PLUS_MINUS": 13,
      "VIDEO_AVAILABLE": 0
    },
    {
      "SEASON_ID": "22004",
      "Player_ID": 2544,
      "Game_ID": "0020401194",
      "GAME_DATE": "Apr 17, 2005",
      "MATCHUP": "CLE @ DET",
      "WL": "L",
      "MIN": 45,
      "FGM": 12,
      "FGA": 35,
      "FG_PCT": 0.343,
      "FG3M": 2,
      "FG3A": 7,
      "FG3_PCT": 0.286,
      "FTM": 11,
      "FTA": 14,
      "FT_PCT": 0.786,
      "OREB": 3,
      "DREB": 8,
      "REB": 11,
      "AST": 6,
      "STL": 0,
      "BLK": 1,
      "TOV": 1,
      "PF": 0,
      "PTS": 37,
      "PLUS_MINUS": -6,
      "VIDEO_AVAILABLE": 0
    },
    {
      "SEASON_ID": "22004",
      "Player_ID": 2544,
      "Game_ID": "0020401174",
      "GAME_DATE": "Apr 15, 2005",
      "MATCHUP": "CLE @ WAS",
      "WL": "L",
      "MIN": 48,
      "FGM": 16,
      "FGA": 33,
      "FG_PCT": 0.485,
      "FG3M": 1,
      "FG3A": 6,
      "FG3_PCT": 0.167,
      "FTM": 5,
      "FTA": 8,
      "FT_PCT": 0.625,
      "OREB": 2,
      "DREB": 4,
      "REB": 6,
      "AST": 6,
      "STL": 1,
      "BLK": 0,
      "TOV": 1,
      "PF": 3,
      "PTS": 38,
      "PLUS_MINUS": -8,
      "VIDEO_AVAILABLE": 0
    },
    {
      "SEASON_ID": "22004",
      "Player_ID": 2544,
      "Game_ID": "0020401171",
      "GAME_DATE": "Apr 14, 2005",
      "MATCHUP": "CLE vs. NYK",
      "WL": "L",
      "MIN": 42,
      "FGM": 7,
      "FGA": 25,
      "FG_PCT": 0.28,
      "FG3M": 4,
      "FG3A": 13,
      "FG3_PCT": 0.308,
      "FTM": 9,
      "FTA": 14,
      "FT_PCT": 0.643,
      "OREB": 1,
      "DREB": 17,
      "REB": 18,
      "AST": 7,
      "STL": 2,
      "BLK": 2,
      "TOV": 4,
      "PF": 3,
      "PTS": 27,
      "PLUS_MINUS": 1,
      "VIDEO_AVAILABLE": 0
    },
    {
      "SEASON_ID": "22004",
      "Player_ID": 2544,
      "Game_ID": "0020401148",
      "GAME_DATE": "Apr 11, 2005",
      "MATCHUP": "CLE @ ORL",
      "WL": "W",
      "MIN": 48,
      "FGM": 12,
      "FGA": 23,
      "FG_PCT": 0.522,
      "FG3M": 1,
      "FG3A": 6,
      "FG3_PCT": 0.167,
      "FTM": 8,
      "FTA": 10,
      "FT_PCT": 0.8,
      "OREB": 1,
      "DREB": 6,
      "REB": 7,
      "AST": 6,
      "STL": 5,
      "BLK": 1,
      "TOV": 2,
      "PF": 4,
      "PTS": 33,
      "PLUS_MINUS": 8,
      "VIDEO_AVAILABLE": 0
    },
    {
      "SEASON_ID": "22004",
      "Player_ID": 2544,
      "Game_ID": "0020401134",
      "GAME_DATE": "Apr 09, 2005",
      "MATCHUP": "CLE vs. MIL",
      "WL": "W",
      "MIN": 47,
      "FGM": 15,
      "FGA": 26,
      "FG_PCT": 0.577,
      "FG3M": 7,
      "FG3A": 13,
      "FG3_PCT": 0.538,
      "FTM": 3,
      "FTA": 3,
      "FT_PCT": 1.0,
      "OREB": 1,
      "DREB": 9,
      "REB": 10,
      "AST": 10,
      "STL": 2,
      "BLK": 1,
      "TOV": 3,
      "PF": 2,
      "PTS": 40,
      "PLUS_MINUS": 13,
      "VIDEO_AVAILABLE": 0
    },
    {
      "SEASON_ID": "22004",
      "Player_ID": 2544,
      "Game_ID": "0020401120",
      "GAME_DATE": "Apr 08, 2005",
      "MATCHUP": "CLE @ PHI",
      "WL": "L",
      "MIN": 48,
      "FGM": 12,
      "FGA": 30,
      "FG_PCT": 0.4,
      "FG3M": 2,
      "FG3A": 6,
      "FG3_PCT": 0.333,
      "FTM": 11,
      "FTA": 11,
      "FT_PCT": 1.0,
      "OREB": 4,
      "DREB": 9,
      "REB": 13,
      "AST": 7,
      "STL": 5,
      "BLK": 0,
      "TOV": 5,
      "PF": 1,
      "PTS": 37,
      "PLUS_MINUS": -5,
      "VIDEO_AVAILABLE": 0
    },
    {
      "SEASON_ID": "22004",
      "Player_ID": 2544,
      "Game_ID": "0020401110",
      "GAME_DATE": "Apr 06, 2005",
      "MATCHUP": "CLE @ IND",
      "WL": "L",
      "MIN": 33,
      "FGM": 9,
      "FGA": 18,
      "FG_PCT": 0.5,
      "FG3M": 0,
      "FG3A": 3,
      "FG3_PCT": 0.0,
      "FTM": 2,
      "FTA": 4,
      "FT_PCT": 0.5,
      "OREB": 2,
      "DREB": 2,
      "REB": 4,
      "AST": 3,
      "STL": 1,
      "BLK": 0,
      "TOV": 2,
      "PF": 2,
      "PTS": 20,
      "PLUS_MINUS": -15,
      "VIDEO_AVAILABLE": 0
    },
    {
      "SEASON_ID": "22004",
      "Player_ID": 2544,
      "Game_ID": "0020401096",
      "GAME_DATE": "Apr 05, 2005",
      "MATCHUP": "CLE vs. NJN",
      "WL": "L",
      "MIN": 40,
      "FGM": 9,
      "FGA": 19,
      "FG_PCT": 0.474,
      "FG3M": 3,
      "FG3A": 6,
      "FG3_PCT": 0.5,
      "FTM": 3,
      "FTA": 6,
      "FT_PCT": 0.5,
      "OREB": 2,
      "DREB": 7,
      "REB": 9,
      "AST": 4,
      "STL": 2,
      "BLK": 2,
      "TOV": 6,
      "PF": 2,
      "PTS": 24,
      "PLUS_MINUS": -21,
      "VIDEO_AVAILABLE": 0
    },
    {
      "SEASON_ID": "22004",
      "Player_ID": 2544,
      "Game_ID": "0020401085",
      "GAME_DATE": "Apr 03, 2005",
      "MATCHUP": "CLE vs. DAL",
      "WL": "W",
      "MIN": 48,
      "FGM": 10,
      "FGA": 23,
      "FG_PCT": 0.435,
      "FG3M": 4,
      "FG3A": 8,
      "FG3_PCT": 0.5,
      "FTM": 13,
      "FTA": 13,
      "FT_PCT": 1.0,
      "OREB": 2,
      "DREB": 8,
      "REB": 10,
      "AST": 7,
      "STL": 2,
      "BLK": 1,
      "TOV": 6,
      "PF": 3,
      "PTS": 37,
      "PLUS_MINUS": 20,
      "VIDEO_AVAILABLE": 0
    },
    {
      "SEASON_ID": "22004",
      "Player_ID": 2544,
      "Game_ID": "0020401072",
      "GAME_DATE": "Apr 01, 2005",
      "MATCHUP": "CLE vs. SAC",
      "WL": "L",
      "MIN": 44,
      "FGM": 13,
      "FGA": 21,
      "FG_PCT": 0.619,
      "FG3M": 2,
      "FG3A": 4,
      "FG3_PCT": 0.5,
      "FTM": 7,
      "FTA": 10,
      "FT_PCT": 0.7,
      "OREB": 0,
      "DREB": 8,
      "REB": 8,
      "AST": 9,
      "STL": 2,
      "BLK": 0,
      "TOV": 7,
      "PF": 2,
      "PTS": 35,
      "PLUS_MINUS": -15,
      "VIDEO_AVAILABLE": 0
    },
    {
      "SEASON_ID": "22004",
      "Player_ID": 2544,
      "Game_ID": "0020401064",
      "GAME_DATE": "Mar 31, 2005",
      "MATCHUP": "CLE @ CHI",
      "WL": "L",
      "MIN": 53,
      "FGM": 10,
      "FGA": 28,
      "FG_PCT": 0.357,
      "FG3M": 1,
      "FG3A": 4,
      "FG3_PCT": 0.25,
      "FTM": 5,
      "FTA": 11,
      "FT_PCT": 0.455,
      "OREB": 4,
      "DREB": 2,
      "REB": 6,
      "AST": 7,
      "STL": 4,
      "BLK": 2,
      "TOV": 3,
      "PF": 5,
      "PTS": 26,
      "PLUS_MINUS": -12,
      "VIDEO_AVAILABLE": 0
    },
    {
      "SEASON_ID": "22004",
      "Player_ID": 2544,
      "Game_ID": "0020401048",
      "GAME_DATE": "Mar 29, 2005",
      "MATCHUP": "CLE vs. LAC",
      "WL": "W",
      "MIN": 41,
      "FGM": 7,
      "FGA": 20,
      "FG_PCT": 0.35,
      "FG3M": 2,
      "FG3A": 8,
      "FG3_PCT": 0.25,
      "FTM": 6,
      "FTA": 7,
      "FT_PCT": 0.857,
      "OREB": 0,
      "DREB": 7,
      "REB": 7,
      "AST": 5,
      "STL": 2,
      "BLK": 1,
      "TOV": 1,
      "PF": 0,
      "PTS": 22,
      "PLUS_MINUS": 11,
      "VIDEO_AVAILABLE": 0
    },
    {
      "SEASON_ID": "22004",
      "Player_ID": 2544,
      "Game_ID": "0020401041",
      "GAME_DATE": "Mar 28, 2005",
      "MATCHUP": "CLE @ NOK",
      "WL": "W",
      "MIN": 53,
      "FGM": 16,
      "FGA": 29,
      "FG_PCT": 0.552,
      "FG3M": 3,
      "FG3A": 10,
      "FG3_PCT": 0.3,
      "FTM": 9,
      "FTA": 11,
      "FT_PCT": 0.818,
      "OREB": 2,
      "DREB": 4,
      "REB": 6,
      "AST": 3,
      "STL": 4,
      "BLK": 0,
      "TOV": 10,
      "PF": 3,
      "PTS": 44,
      "PLUS_MINUS": 1,
      "VIDEO_AVAILABLE": 0
    },
    {
      "SEASON_ID": "22004",
      "Player_ID": 2544,
      "Game_ID": "0020401029",
      "GAME_DATE": "Mar 26, 2005",
      "MATCHUP": "CLE @ DAL",
      "WL": "L",
      "MIN": 36,
      "FGM": 7,
      "FGA": 17,
      "FG_PCT": 0.412,
      "FG3M": 0,
      "FG3A": 2,
      "FG3_PCT": 0.0,
      "FTM": 5,
      "FTA": 6,
      "FT_PCT": 0.833,
      "OREB": 1,
      "DREB": 3,
      "REB": 4,
      "AST": 6,
      "STL": 0,
      "BLK": 0,
      "TOV": 3,
      "PF": 1,
      "PTS": 19,
      "PLUS_MINUS": -24,
      "VIDEO_AVAILABLE": 0
    },
    {
      "SEASON_ID": "22004",
      "Player_ID": 2544,
      "Game_ID": "0020401008",
      "GAME_DATE": "Mar 24, 2005",
      "MATCHUP": "CLE @ HOU",
      "WL": "L",
      "MIN": 42,
      "FGM": 7,
      "FGA": 22,
      "FG_PCT": 0.318,
      "FG3M": 1,
      "FG3A": 4,
      "FG3_PCT": 0.25,
      "FTM": 4,
      "FTA": 7,
      "FT_PCT": 0.571,
      "OREB": 0,
      "DREB": 4,
      "REB": 4,
      "AST": 8,
      "STL": 1,
      "BLK": 0,
      "TOV": 2,
      "PF": 1,
      "PTS": 19,
      "PLUS_MINUS": -17,
      "VIDEO_AVAILABLE": 0
    },
    {
      "SEASON_ID": "22004",
      "Player_ID": 2544,
      "Game_ID": "0020400990",
      "GAME_DATE": "Mar 22, 2005",
      "MATCHUP": "CLE vs. DET",
      "WL": "W",
      "MIN": 43,
      "FGM": 11,
      "FGA": 24,
      "FG_PCT": 0.458,
      "FG3M": 2,
      "FG3A": 7,
      "FG3_PCT": 0.286,
      "FTM": 5,
      "FTA": 8,
      "FT_PCT": 0.625,
      "OREB": 1,
      "DREB": 5,
      "REB": 6,
      "AST": 6,
      "STL": 1,
      "BLK": 0,
      "TOV": 0,
      "PF": 1,
      "PTS": 29,
      "PLUS_MINUS": 21,
      "VIDEO_AVAILABLE": 0
    },
    {
      "SEASON_ID": "22004",
      "Player_ID": 2544,
      "Game_ID": "0020400977",
      "GAME_DATE": "Mar 20, 2005",
      "MATCHUP": "CLE @ TOR",
      "WL": "L",
      "MIN": 48,
      "FGM": 18,
      "FGA": 36,
      "FG_PCT": 0.5,
      "FG3M": 6,
      "FG3A": 12,
      "FG3_PCT": 0.5,
      "FTM": 14,
      "FTA": 15,
      "FT_PCT": 0.933,
      "OREB": 2,
      "DREB": 8,
      "REB": 10,
      "AST": 5,
      "STL": 2,
      "BLK": 0,
      "TOV": 4,
      "PF": 0,
      "PTS": 56,
      "PLUS_MINUS": -7,
      "VIDEO_AVAILABLE": 0
    },
    {
      "SEASON_ID": "22004",
      "Player_ID": 2544,
      "Game_ID": "0020400959",
      "GAME_DATE": "Mar 18, 2005",
      "MATCHUP": "CLE vs. PHI",
      "WL": "L",
      "MIN": 46,
      "FGM": 3,
      "FGA": 20,
      "FG_PCT": 0.15,
      "FG3M": 0,
      "FG3A": 4,
      "FG3_PCT": 0.0,
      "FTM": 10,
      "FTA": 12,
      "FT_PCT": 0.833,
      "OREB": 0,
      "DREB": 8,
      "REB": 8,
      "AST": 8,
      "STL": 4,
      "BLK": 0,
      "TOV": 4,
      "PF": 0,
      "PTS": 16,
      "PLUS_MINUS": -8,
      "VIDEO_AVAILABLE": 0
    },
    {
      "SEASON_ID": "22004",
      "Player_ID": 2544,
      "Game_ID": "0020400948",
      "GAME_DATE": "Mar 16, 2005",
      "MATCHUP": "CLE @ MIL",
      "WL": "L",
      "MIN": 45,
      "FGM": 13,
      "FGA": 26,
      "FG_PCT": 0.5,
      "FG3M": 4,
      "FG3A": 9,
      "FG3_PCT": 0.444,
      "FTM": 4,
      "FTA": 7,
      "FT_PCT": 0.571,
      "OREB": 1,
      "DREB": 6,
      "REB": 7,
      "AST": 6,
      "STL": 1,
      "BLK": 0,
      "TOV": 5,
      "PF": 0,
      "PTS": 34,
      "PLUS_MINUS": -14,
      "VIDEO_AVAILABLE": 0
    },
    {
      "SEASON_ID": "22004",
      "Player_ID": 2544,
      "Game_ID": "0020400938",
      "GAME_DATE": "Mar 15, 2005",
      "MATCHUP": "CLE vs. UTA",
      "WL": "W",
      "MIN": 35,
      "FGM": 11,
      "FGA": 15,
      "FG_PCT": 0.733,
      "FG3M": 2,
      "FG3A": 5,
      "FG3_PCT": 0.4,
      "FTM": 12,
      "FTA": 16,
      "FT_PCT": 0.75,
      "OREB": 2,
      "DREB": 7,
      "REB": 9,
      "AST": 2,
      "STL": 0,
      "BLK": 1,
      "TOV": 1,
      "PF": 1,
      "PTS": 36,
      "PLUS_MINUS": 22,
      "VIDEO_AVAILABLE": 0
    },
    {
      "SEASON_ID": "22004",
      "Player_ID": 2544,
      "Game_ID": "0020400928",
      "GAME_DATE": "Mar 13, 2005",
      "MATCHUP": "CLE vs. IND",
      "WL": "W",
      "MIN": 44,
      "FGM": 12,
      "FGA": 23,
      "FG_PCT": 0.522,
      "FG3M": 1,
      "FG3A": 5,
      "FG3_PCT": 0.2,
      "FTM": 10,
      "FTA": 11,
      "FT_PCT": 0.909,
      "OREB": 2,
      "DREB": 3,
      "REB": 5,
      "AST": 5,
      "STL": 1,
      "BLK": 0,
      "TOV": 4,
      "PF": 1,
      "PTS": 35,
      "PLUS_MINUS": 12,
      "VIDEO_AVAILABLE": 0
    },
    {
      "SEASON_ID": "22004",
      "Player_ID": 2544,
      "Game_ID": "0020400887",
      "GAME_DATE": "Mar 08, 2005",
      "MATCHUP": "CLE vs. ORL",
      "WL": "W",
      "MIN": 40,
      "FGM": 9,
      "FGA": 22,
      "FG_PCT": 0.409,
      "FG3M": 2,
      "FG3A": 6,
      "FG3_PCT": 0.333,
      "FTM": 3,
      "FTA": 4,
      "FT_PCT": 0.75,
      "OREB": 0,
      "DREB": 7,
      "REB": 7,
      "AST": 8,
      "STL": 1,
      "BLK": 1,
      "TOV": 1,
      "PF": 3,
      "PTS": 23,
      "PLUS_MINUS": 18,
      "VIDEO_AVAILABLE": 0
    },
    {
      "SEASON_ID": "22004",
      "Player_ID": 2544,
      "Game_ID": "0020400878",
      "GAME_DATE": "Mar 06, 2005",
      "MATCHUP": "CLE vs. MIA",
      "WL": "L",
      "MIN": 41,
      "FGM": 9,
      "FGA": 19,
      "FG_PCT": 0.474,
      "FG3M": 0,
      "FG3A": 1,
      "FG3_PCT": 0.0,
      "FTM": 5,
      "FTA": 7,
      "FT_PCT": 0.714,
      "OREB": 0,
      "DREB": 4,
      "REB": 4,
      "AST": 5,
      "STL": 2,
      "BLK": 0,
      "TOV": 1,
      "PF": 1,
      "PTS": 23,
      "PLUS_MINUS": -17,
      "VIDEO_AVAILABLE": 0
    },
    {
      "SEASON_ID": "22004",
      "Player_ID": 2544,
      "Game_ID": "0020400854",
      "GAME_DATE": "Mar 04, 2005",
      "MATCHUP": "CLE @ PHI",
      "WL": "L",
      "MIN": 40,
      "FGM": 12,
      "FGA": 21,
      "FG_PCT": 0.571,
      "FG3M": 0,
      "FG3A": 1,
      "FG3_PCT": 0.0,
      "FTM": 10,
      "FTA": 12,
      "FT_PCT": 0.833,
      "OREB": 1,
      "DREB": 6,
      "REB": 7,
      "AST": 7,
      "STL": 4,
      "BLK": 0,
      "TOV": 6,
      "PF": 1,
      "PTS": 34,
      "PLUS_MINUS": -10,
      "VIDEO_AVAILABLE": 0
    },
    {
      "SEASON_ID": "22004",
      "Player_ID": 2544,
      "Game_ID": "0020400844",
      "GAME_DATE": "Mar 02, 2005",
      "MATCHUP": "CLE vs. SEA",
      "WL": "L",
      "MIN": 41,
      "FGM": 11,
      "FGA": 20,
      "FG_PCT": 0.55,
      "FG3M": 5,
      "FG3A": 7,
      "FG3_PCT": 0.714,
      "FTM": 5,
      "FTA": 8,
      "FT_PCT": 0.625,
      "OREB": 0,
      "DREB": 5,
      "REB": 5,
      "AST": 5,
      "STL": 0,
      "BLK": 0,
      "TOV": 4,
      "PF": 2,
      "PTS": 32,
      "PLUS_MINUS": -7,
      "VIDEO_AVAILABLE": 0
    },
    {
      "SEASON_ID": "22004",
      "Player_ID": 2544,
      "Game_ID": "0020400830",
      "GAME_DATE": "Feb 28, 2005",
      "MATCHUP": "CLE vs. SAS",
      "WL": "L",
      "MIN": 45,
      "FGM": 6,
      "FGA": 22,
      "FG_PCT": 0.273,
      "FG3M": 1,
      "FG3A": 4,
      "FG3_PCT": 0.25,
      "FTM": 7,
      "FTA": 10,
      "FT_PCT": 0.7,
      "OREB": 1,
      "DREB": 7,
      "REB": 8,
      "AST": 7,
      "STL": 0,
      "BLK": 0,
      "TOV": 2,
      "PF": 3,
      "PTS": 20,
      "PLUS_MINUS": 2,
      "VIDEO_AVAILABLE": 0
    },
    {
      "SEASON_ID": "22004",
      "Player_ID": 2544,
      "Game_ID": "0020400820",
      "GAME_DATE": "Feb 27, 2005",
      "MATCHUP": "CLE @ NJN",
      "WL": "L",
      "MIN": 45,
      "FGM": 9,
      "FGA": 20,
      "FG_PCT": 0.45,
      "FG3M": 1,
      "FG3A": 2,
      "FG3_PCT": 0.5,
      "FTM": 9,
      "FTA": 10,
      "FT_PCT": 0.9,
      "OREB": 1,
      "DREB": 3,
      "REB": 4,
      "AST": 7,
      "STL": 2,
      "BLK": 0,
      "TOV": 5,
      "PF": 4,
      "PTS": 28,
      "PLUS_MINUS": -10,
      "VIDEO_AVAILABLE": 0
    },
    {
      "SEASON_ID": "22004",
      "Player_ID": 2544,
      "Game_ID": "0020400805",
      "GAME_DATE": "Feb 25, 2005",
      "MATCHUP": "CLE @ IND",
      "WL": "L",
      "MIN": 41,
      "FGM": 9,
      "FGA": 25,
      "FG_PCT": 0.36,
      "FG3M": 0,
      "FG3A": 1,
      "FG3_PCT": 0.0,
      "FTM": 3,
      "FTA": 4,
      "FT_PCT": 0.75,
      "OREB": 3,
      "DREB": 4,
      "REB": 7,
      "AST": 5,
      "STL": 2,
      "BLK": 1,
      "TOV": 2,
      "PF": 0,
      "PTS": 21,
      "PLUS_MINUS": -11,
      "VIDEO_AVAILABLE": 0
    },
    {
      "SEASON_ID": "22004",
      "Player_ID": 2544,
      "Game_ID": "0020400791",
      "GAME_DATE": "Feb 23, 2005",
      "MATCHUP": "CLE vs. CHI",
      "WL": "W",
      "MIN": 44,
      "FGM": 8,
      "FGA": 17,
      "FG_PCT": 0.471,
      "FG3M": 1,
      "FG3A": 1,
      "FG3_PCT": 1.0,
      "FTM": 10,
      "FTA": 15,
      "FT_PCT": 0.667,
      "OREB": 1,
      "DREB": 5,
      "REB": 6,
      "AST": 11,
      "STL": 5,
      "BLK": 0,
      "TOV": 3,
      "PF": 2,
      "PTS": 27,
      "PLUS_MINUS": 7,
      "VIDEO_AVAILABLE": 0
    },
    {
      "SEASON_ID": "22004",
      "Player_ID": 2544,
      "Game_ID": "0020400780",
      "GAME_DATE": "Feb 17, 2005",
      "MATCHUP": "CLE @ MIN",
      "WL": "L",
      "MIN": 41,
      "FGM": 10,
      "FGA": 19,
      "FG_PCT": 0.526,
      "FG3M": 1,
      "FG3A": 2,
      "FG3_PCT": 0.5,
      "FTM": 5,
      "FTA": 6,
      "FT_PCT": 0.833,
      "OREB": 2,
      "DREB": 5,
      "REB": 7,
      "AST": 8,
      "STL": 1,
      "BLK": 0,
      "TOV": 2,
      "PF": 0,
      "PTS": 26,
      "PLUS_MINUS": -1,
      "VIDEO_AVAILABLE": 0
    },
    {
      "SEASON_ID": "22004",
      "Player_ID": 2544,
      "Game_ID": "0020400773",
      "GAME_DATE": "Feb 16, 2005",
      "MATCHUP": "CLE vs. ATL",
      "WL": "W",
      "MIN": 37,
      "FGM": 11,
      "FGA": 20,
      "FG_PCT": 0.55,
      "FG3M": 2,
      "FG3A": 2,
      "FG3_PCT": 1.0,
      "FTM": 4,
      "FTA": 5,
      "FT_PCT": 0.8,
      "OREB": 0,
      "DREB": 5,
      "REB": 5,
      "AST": 6,
      "STL": 3,
      "BLK": 0,
      "TOV": 3,
      "PF": 0,
      "PTS": 28,
      "PLUS_MINUS": 27,
      "VIDEO_AVAILABLE": 0
    },
    {
      "SEASON_ID": "22004",
      "Player_ID": 2544,
      "Game_ID": "0020400746",
      "GAME_DATE": "Feb 13, 2005",
      "MATCHUP": "CLE vs. LAL",
      "WL": "W",
      "MIN": 46,
      "FGM": 8,
      "FGA": 20,
      "FG_PCT": 0.4,
      "FG3M": 0,
      "FG3A": 0,
      "FG3_PCT": 0.0,
      "FTM": 9,
      "FTA": 10,
      "FT_PCT": 0.9,
      "OREB": 2,
      "DREB": 6,
      "REB": 8,
      "AST": 9,
      "STL": 3,
      "BLK": 1,
      "TOV": 3,
      "PF": 3,
      "PTS": 25,
      "PLUS_MINUS": 9,
      "VIDEO_AVAILABLE": 0
    },
    {
      "SEASON_ID": "22004",
      "Player_ID": 2544,
      "Game_ID": "0020400736",
      "GAME_DATE": "Feb 11, 2005",
      "MATCHUP": "CLE vs. DEN",
      "WL": "L",
      "MIN": 43,
      "FGM": 12,
      "FGA": 29,
      "FG_PCT": 0.414,
      "FG3M": 1,
      "FG3A": 6,
      "FG3_PCT": 0.167,
      "FTM": 10,
      "FTA": 12,
      "FT_PCT": 0.833,
      "OREB": 2,
      "DREB": 4,
      "REB": 6,
      "AST": 6,
      "STL": 1,
      "BLK": 0,
      "TOV": 4,
      "PF": 2,
      "PTS": 35,
      "PLUS_MINUS": -13,
      "VIDEO_AVAILABLE": 0
    },
    {
      "SEASON_ID": "22004",
      "Player_ID": 2544,
      "Game_ID": "0020400710",
      "GAME_DATE": "Feb 08, 2005",
      "MATCHUP": "CLE vs. TOR",
      "WL": "W",
      "MIN": 36,
      "FGM": 6,
      "FGA": 14,
      "FG_PCT": 0.429,
      "FG3M": 0,
      "FG3A": 3,
      "FG3_PCT": 0.0,
      "FTM": 3,
      "FTA": 4,
      "FT_PCT": 0.75,
      "OREB": 1,
      "DREB": 7,
      "REB": 8,
      "AST": 11,
      "STL": 3,
      "BLK": 0,
      "TOV": 2,
      "PF": 1,
      "PTS": 15,
      "PLUS_MINUS": 15,
      "VIDEO_AVAILABLE": 0
    },
    {
      "SEASON_ID": "22004",
      "Player_ID": 2544,
      "Game_ID": "0020400693",
      "GAME_DATE": "Feb 05, 2005",
      "MATCHUP": "CLE vs. ORL",
      "WL": "W",
      "MIN": 45,
      "FGM": 9,
      "FGA": 21,
      "FG_PCT": 0.429,
      "FG3M": 0,
      "FG3A": 3,
      "FG3_PCT": 0.0,
      "FTM": 12,
      "FTA": 13,
      "FT_PCT": 0.923,
      "OREB": 0,
      "DREB": 6,
      "REB": 6,
      "AST": 9,
      "STL": 2,
      "BLK": 0,
      "TOV": 1,
      "PF": 2,
      "PTS": 30,
      "PLUS_MINUS": 10,
      "VIDEO_AVAILABLE": 0
    },
    {
      "SEASON_ID": "22004",
      "Player_ID": 2544,
      "Game_ID": "0020400677",
      "GAME_DATE": "Feb 03, 2005",
      "MATCHUP": "CLE @ MIA",
      "WL": "L",
      "MIN": 46,
      "FGM": 11,
      "FGA": 23,
      "FG_PCT": 0.478,
      "FG3M": 1,
      "FG3A": 3,
      "FG3_PCT": 0.333,
      "FTM": 8,
      "FTA": 12,
      "FT_PCT": 0.667,
      "OREB": 2,
      "DREB": 0,
      "REB": 2,
      "AST": 10,
      "STL": 3,
      "BLK": 0,
      "TOV": 2,
      "PF": 2,
      "PTS": 31,
      "PLUS_MINUS": -8,
      "VIDEO_AVAILABLE": 0
    },
    {
      "SEASON_ID": "22004",
      "Player_ID": 2544,
      "Game_ID": "0020400660",
      "GAME_DATE": "Feb 01, 2005",
      "MATCHUP": "CLE @ ORL",
      "WL": "L",
      "MIN": 43,
      "FGM": 10,
      "FGA": 20,
      "FG_PCT": 0.5,
      "FG3M": 0,
      "FG3A": 3,
      "FG3_PCT": 0.0,
      "FTM": 8,
      "FTA": 13,
      "FT_PCT": 0.615,
      "OREB": 2,
      "DREB": 3,
      "REB": 5,
      "AST": 7,
      "STL": 0,
      "BLK": 1,
      "TOV": 3,
      "PF": 2,
      "PTS": 28,
      "PLUS_MINUS": -3,
      "VIDEO_AVAILABLE": 0
    },
    {
      "SEASON_ID": "22004",
      "Player_ID": 2544,
      "Game_ID": "0020400615",
      "GAME_DATE": "Jan 26, 2005",
      "MATCHUP": "CLE vs. MEM",
      "WL": "W",
      "MIN": 42,
      "FGM": 10,
      "FGA": 16,
      "FG_PCT": 0.625,
      "FG3M": 4,
      "FG3A": 6,
      "FG3_PCT": 0.667,
      "FTM": 3,
      "FTA": 4,
      "FT_PCT": 0.75,
      "OREB": 1,
      "DREB": 8,
      "REB": 9,
      "AST": 15,
      "STL": 3,
      "BLK": 2,
      "TOV": 5,
      "PF": 1,
      "PTS": 27,
      "PLUS_MINUS": 7,
      "VIDEO_AVAILABLE": 0
    },
    {
      "SEASON_ID": "22004",
      "Player_ID": 2544,
      "Game_ID": "0020400599",
      "GAME_DATE": "Jan 24, 2005",
      "MATCHUP": "CLE vs. WAS",
      "WL": "L",
      "MIN": 48,
      "FGM": 12,
      "FGA": 26,
      "FG_PCT": 0.462,
      "FG3M": 1,
      "FG3A": 1,
      "FG3_PCT": 1.0,
      "FTM": 6,
      "FTA": 10,
      "FT_PCT": 0.6,
      "OREB": 4,
      "DREB": 6,
      "REB": 10,
      "AST": 8,
      "STL": 2,
      "BLK": 1,
      "TOV": 5,
      "PF": 3,
      "PTS": 31,
      "PLUS_MINUS": -9,
      "VIDEO_AVAILABLE": 0
    },
    {
      "SEASON_ID": "22004",
      "Player_ID": 2544,
      "Game_ID": "0020400591",
      "GAME_DATE": "Jan 22, 2005",
      "MATCHUP": "CLE @ GSW",
      "WL": "W",
      "MIN": 43,
      "FGM": 13,
      "FGA": 24,
      "FG_PCT": 0.542,
      "FG3M": 0,
      "FG3A": 1,
      "FG3_PCT": 0.0,
      "FTM": 2,
      "FTA": 2,
      "FT_PCT": 1.0,
      "OREB": 1,
      "DREB": 11,
      "REB": 12,
      "AST": 10,
      "STL": 1,
      "BLK": 1,
      "TOV": 3,
      "PF": 1,
      "PTS": 28,
      "PLUS_MINUS": 19,
      "VIDEO_AVAILABLE": 0
    },
    {
      "SEASON_ID": "22004",
      "Player_ID": 2544,
      "Game_ID": "0020400572",
      "GAME_DATE": "Jan 20, 2005",
      "MATCHUP": "CLE @ SAC",
      "WL": "L",
      "MIN": 37,
      "FGM": 9,
      "FGA": 19,
      "FG_PCT": 0.474,
      "FG3M": 0,
      "FG3A": 1,
      "FG3_PCT": 0.0,
      "FTM": 0,
      "FTA": 1,
      "FT_PCT": 0.0,
      "OREB": 1,
      "DREB": 7,
      "REB": 8,
      "AST": 6,
      "STL": 1,
      "BLK": 0,
      "TOV": 3,
      "PF": 0,
      "PTS": 18,
      "PLUS_MINUS": -24,
      "VIDEO_AVAILABLE": 0
    },
    {
      "SEASON_ID": "22004",
      "Player_ID": 2544,
      "Game_ID": "0020400568",
      "GAME_DATE": "Jan 19, 2005",
      "MATCHUP": "CLE @ POR",
      "WL": "W",
      "MIN": 44,
      "FGM": 11,
      "FGA": 16,
      "FG_PCT": 0.688,
      "FG3M": 1,
      "FG3A": 1,
      "FG3_PCT": 1.0,
      "FTM": 4,
      "FTA": 6,
      "FT_PCT": 0.667,
      "OREB": 1,
      "DREB": 10,
      "REB": 11,
      "AST": 10,
      "STL": 4,
      "BLK": 0,
      "TOV": 2,
      "PF": 4,
      "PTS": 27,
      "PLUS_MINUS": 0,
      "VIDEO_AVAILABLE": 0
    },
    {
      "SEASON_ID": "22004",
      "Player_ID": 2544,
      "Game_ID": "0020400543",
      "GAME_DATE": "Jan 16, 2005",
      "MATCHUP": "CLE @ SEA",
      "WL": "L",
      "MIN": 44,
      "FGM": 14,
      "FGA": 30,
      "FG_PCT": 0.467,
      "FG3M": 3,
      "FG3A": 7,
      "FG3_PCT": 0.429,
      "FTM": 4,
      "FTA": 6,
      "FT_PCT": 0.667,
      "OREB": 2,
      "DREB": 3,
      "REB": 5,
      "AST": 11,
      "STL": 4,
      "BLK": 1,
      "TOV": 1,
      "PF": 4,
      "PTS": 35,
      "PLUS_MINUS": -7,
      "VIDEO_AVAILABLE": 0
    },
    {
      "SEASON_ID": "22004",
      "Player_ID": 2544,
      "Game_ID": "0020400539",
      "GAME_DATE": "Jan 15, 2005",
      "MATCHUP": "CLE @ UTA",
      "WL": "W",
      "MIN": 41,
      "FGM": 9,
      "FGA": 20,
      "FG_PCT": 0.45,
      "FG3M": 0,
      "FG3A": 1,
      "FG3_PCT": 0.0,
      "FTM": 9,
      "FTA": 14,
      "FT_PCT": 0.643,
      "OREB": 1,
      "DREB": 7,
      "REB": 8,
      "AST": 5,
      "STL": 5,
      "BLK": 0,
      "TOV": 3,
      "PF": 2,
      "PTS": 27,
      "PLUS_MINUS": 11,
      "VIDEO_AVAILABLE": 0
    },
    {
      "SEASON_ID": "22004",
      "Player_ID": 2544,
      "Game_ID": "0020400518",
      "GAME_DATE": "Jan 13, 2005",
      "MATCHUP": "CLE @ LAL",
      "WL": "L",
      "MIN": 44,
      "FGM": 12,
      "FGA": 26,
      "FG_PCT": 0.462,
      "FG3M": 1,
      "FG3A": 4,
      "FG3_PCT": 0.25,
      "FTM": 3,
      "FTA": 4,
      "FT_PCT": 0.75,
      "OREB": 3,
      "DREB": 10,
      "REB": 13,
      "AST": 9,
      "STL": 1,
      "BLK": 1,
      "TOV": 4,
      "PF": 1,
      "PTS": 28,
      "PLUS_MINUS": -1,
      "VIDEO_AVAILABLE": 0
    },
    {
      "SEASON_ID": "22004",
      "Player_ID": 2544,
      "Game_ID": "0020400497",
      "GAME_DATE": "Jan 11, 2005",
      "MATCHUP": "CLE vs. CHA",
      "WL": "W",
      "MIN": 49,
      "FGM": 11,
      "FGA": 24,
      "FG_PCT": 0.458,
      "FG3M": 2,
      "FG3A": 5,
      "FG3_PCT": 0.4,
      "FTM": 5,
      "FTA": 7,
      "FT_PCT": 0.714,
      "OREB": 1,
      "DREB": 7,
      "REB": 8,
      "AST": 9,
      "STL": 2,
      "BLK": 1,
      "TOV": 8,
      "PF": 1,
      "PTS": 29,
      "PLUS_MINUS": 7,
      "VIDEO_AVAILABLE": 0
    },
    {
      "SEASON_ID": "22004",
      "Player_ID": 2544,
      "Game_ID": "0020400478",
      "GAME_DATE": "Jan 08, 2005",
      "MATCHUP": "CLE vs. NYK",
      "WL": "W",
      "MIN": 32,
      "FGM": 10,
      "FGA": 14,
      "FG_PCT": 0.714,
      "FG3M": 0,
      "FG3A": 0,
      "FG3_PCT": 0.0,
      "FTM": 2,
      "FTA": 2,
      "FT_PCT": 1.0,
      "OREB": 1,
      "DREB": 2,
      "REB": 3,
      "AST": 4,
      "STL": 0,
      "BLK": 2,
      "TOV": 8,
      "PF": 2,
      "PTS": 22,
      "PLUS_MINUS": 5,
      "VIDEO_AVAILABLE": 0
    },
    {
      "SEASON_ID": "22004",
      "Player_ID": 2544,
      "Game_ID": "0020400457",
      "GAME_DATE": "Jan 05, 2005",
      "MATCHUP": "CLE vs. ATL",
      "WL": "W",
      "MIN": 40,
      "FGM": 7,
      "FGA": 14,
      "FG_PCT": 0.5,
      "FG3M": 2,
      "FG3A": 5,
      "FG3_PCT": 0.4,
      "FTM": 4,
      "FTA": 6,
      "FT_PCT": 0.667,
      "OREB": 1,
      "DREB": 5,
      "REB": 6,
      "AST": 9,
      "STL": 1,
      "BLK": 1,
      "TOV": 2,
      "PF": 4,
      "PTS": 20,
      "PLUS_MINUS": 10,
      "VIDEO_AVAILABLE": 0
    },
    {
      "SEASON_ID": "22004",
      "Player_ID": 2544,
      "Game_ID": "0020400442",
      "GAME_DATE": "Jan 03, 2005",
      "MATCHUP": "CLE @ CHA",
      "WL": "W",
      "MIN": 41,
      "FGM": 11,
      "FGA": 19,
      "FG_PCT": 0.579,
      "FG3M": 0,
      "FG3A": 3,
      "FG3_PCT": 0.0,
      "FTM": 4,
      "FTA": 6,
      "FT_PCT": 0.667,
      "OREB": 2,
      "DREB": 6,
      "REB": 8,
      "AST": 6,
      "STL": 2,
      "BLK": 0,
      "TOV": 1,
      "PF": 3,
      "PTS": 26,
      "PLUS_MINUS": 14,
      "VIDEO_AVAILABLE": 0
    },
    {
      "SEASON_ID": "22004",
      "Player_ID": 2544,
      "Game_ID": "0020400411",
      "GAME_DATE": "Dec 29, 2004",
      "MATCHUP": "CLE vs. HOU",
      "WL": "L",
      "MIN": 17,
      "FGM": 0,
      "FGA": 5,
      "FG_PCT": 0.0,
      "FG3M": 0,
      "FG3A": 1,
      "FG3_PCT": 0.0,
      "FTM": 3,
      "FTA": 5,
      "FT_PCT": 0.6,
      "OREB": 0,
      "DREB": 3,
      "REB": 3,
      "AST": 5,
      "STL": 0,
      "BLK": 0,
      "TOV": 0,
      "PF": 0,
      "PTS": 3,
      "PLUS_MINUS": -10,
      "VIDEO_AVAILABLE": 0
    },
    {
      "SEASON_ID": "22004",
      "Player_ID": 2544,
      "Game_ID": "0020400401",
      "GAME_DATE": "Dec 28, 2004",
      "MATCHUP": "CLE @ ATL",
      "WL": "W",
      "MIN": 46,
      "FGM": 13,
      "FGA": 25,
      "FG_PCT": 0.52,
      "FG3M": 3,
      "FG3A": 5,
      "FG3_PCT": 0.6,
      "FTM": 11,
      "FTA": 14,
      "FT_PCT": 0.786,
      "OREB": 1,
      "DREB": 8,
      "REB": 9,
      "AST": 7,
      "STL": 1,
      "BLK": 0,
      "TOV": 1,
      "PF": 2,
      "PTS": 40,
      "PLUS_MINUS": 8,
      "VIDEO_AVAILABLE": 0
    },
    {
      "SEASON_ID": "22004",
      "Player_ID": 2544,
      "Game_ID": "0020400384",
      "GAME_DATE": "Dec 26, 2004",
      "MATCHUP": "CLE vs. NOK",
      "WL": "W",
      "MIN": 45,
      "FGM": 7,
      "FGA": 16,
      "FG_PCT": 0.438,
      "FG3M": 0,
      "FG3A": 1,
      "FG3_PCT": 0.0,
      "FTM": 8,
      "FTA": 9,
      "FT_PCT": 0.889,
      "OREB": 1,
      "DREB": 8,
      "REB": 9,
      "AST": 14,
      "STL": 4,
      "BLK": 1,
      "TOV": 5,
      "PF": 2,
      "PTS": 22,
      "PLUS_MINUS": 8,
      "VIDEO_AVAILABLE": 0
    },
    {
      "SEASON_ID": "22004",
      "Player_ID": 2544,
      "Game_ID": "0020400370",
      "GAME_DATE": "Dec 22, 2004",
      "MATCHUP": "CLE @ NJN",
      "WL": "L",
      "MIN": 42,
      "FGM": 7,
      "FGA": 18,
      "FG_PCT": 0.389,
      "FG3M": 1,
      "FG3A": 1,
      "FG3_PCT": 1.0,
      "FTM": 8,
      "FTA": 10,
      "FT_PCT": 0.8,
      "OREB": 1,
      "DREB": 8,
      "REB": 9,
      "AST": 9,
      "STL": 1,
      "BLK": 0,
      "TOV": 4,
      "PF": 2,
      "PTS": 23,
      "PLUS_MINUS": -3,
      "VIDEO_AVAILABLE": 0
    },
    {
      "SEASON_ID": "22004",
      "Player_ID": 2544,
      "Game_ID": "0020400361",
      "GAME_DATE": "Dec 21, 2004",
      "MATCHUP": "CLE vs. MIN",
      "WL": "W",
      "MIN": 43,
      "FGM": 10,
      "FGA": 18,
      "FG_PCT": 0.556,
      "FG3M": 0,
      "FG3A": 1,
      "FG3_PCT": 0.0,
      "FTM": 6,
      "FTA": 8,
      "FT_PCT": 0.75,
      "OREB": 0,
      "DREB": 6,
      "REB": 6,
      "AST": 12,
      "STL": 1,
      "BLK": 0,
      "TOV": 2,
      "PF": 2,
      "PTS": 26,
      "PLUS_MINUS": 13,
      "VIDEO_AVAILABLE": 0
    },
    {
      "SEASON_ID": "22004",
      "Player_ID": 2544,
      "Game_ID": "0020400343",
      "GAME_DATE": "Dec 18, 2004",
      "MATCHUP": "CLE vs. BOS",
      "WL": "L",
      "MIN": 40,
      "FGM": 12,
      "FGA": 25,
      "FG_PCT": 0.48,
      "FG3M": 3,
      "FG3A": 5,
      "FG3_PCT": 0.6,
      "FTM": 4,
      "FTA": 8,
      "FT_PCT": 0.5,
      "OREB": 1,
      "DREB": 4,
      "REB": 5,
      "AST": 4,
      "STL": 3,
      "BLK": 1,
      "TOV": 4,
      "PF": 6,
      "PTS": 31,
      "PLUS_MINUS": -1,
      "VIDEO_AVAILABLE": 0
    },
    {
      "SEASON_ID": "22004",
      "Player_ID": 2544,
      "Game_ID": "0020400326",
      "GAME_DATE": "Dec 16, 2004",
      "MATCHUP": "CLE @ DET",
      "WL": "L",
      "MIN": 45,
      "FGM": 4,
      "FGA": 21,
      "FG_PCT": 0.19,
      "FG3M": 0,
      "FG3A": 2,
      "FG3_PCT": 0.0,
      "FTM": 3,
      "FTA": 5,
      "FT_PCT": 0.6,
      "OREB": 1,
      "DREB": 8,
      "REB": 9,
      "AST": 7,
      "STL": 4,
      "BLK": 1,
      "TOV": 3,
      "PF": 2,
      "PTS": 11,
      "PLUS_MINUS": -8,
      "VIDEO_AVAILABLE": 0
    },
    {
      "SEASON_ID": "22004",
      "Player_ID": 2544,
      "Game_ID": "0020400319",
      "GAME_DATE": "Dec 15, 2004",
      "MATCHUP": "CLE vs. POR",
      "WL": "W",
      "MIN": 37,
      "FGM": 10,
      "FGA": 18,
      "FG_PCT": 0.556,
      "FG3M": 2,
      "FG3A": 3,
      "FG3_PCT": 0.667,
      "FTM": 3,
      "FTA": 3,
      "FT_PCT": 1.0,
      "OREB": 2,
      "DREB": 9,
      "REB": 11,
      "AST": 7,
      "STL": 3,
      "BLK": 2,
      "TOV": 3,
      "PF": 1,
      "PTS": 25,
      "PLUS_MINUS": 18,
      "VIDEO_AVAILABLE": 0
    },
    {
      "SEASON_ID": "22004",
      "Player_ID": 2544,
      "Game_ID": "0020400303",
      "GAME_DATE": "Dec 13, 2004",
      "MATCHUP": "CLE @ MEM",
      "WL": "W",
      "MIN": 46,
      "FGM": 14,
      "FGA": 22,
      "FG_PCT": 0.636,
      "FG3M": 1,
      "FG3A": 3,
      "FG3_PCT": 0.333,
      "FTM": 2,
      "FTA": 4,
      "FT_PCT": 0.5,
      "OREB": 0,
      "DREB": 5,
      "REB": 5,
      "AST": 8,
      "STL": 7,
      "BLK": 0,
      "TOV": 3,
      "PF": 2,
      "PTS": 31,
      "PLUS_MINUS": 10,
      "VIDEO_AVAILABLE": 0
    },
    {
      "SEASON_ID": "22004",
      "Player_ID": 2544,
      "Game_ID": "0020400292",
      "GAME_DATE": "Dec 11, 2004",
      "MATCHUP": "CLE @ SAS",
      "WL": "L",
      "MIN": 42,
      "FGM": 10,
      "FGA": 19,
      "FG_PCT": 0.526,
      "FG3M": 1,
      "FG3A": 3,
      "FG3_PCT": 0.333,
      "FTM": 2,
      "FTA": 2,
      "FT_PCT": 1.0,
      "OREB": 3,
      "DREB": 3,
      "REB": 6,
      "AST": 10,
      "STL": 4,
      "BLK": 0,
      "TOV": 3,
      "PF": 2,
      "PTS": 23,
      "PLUS_MINUS": -18,
      "VIDEO_AVAILABLE": 0
    },
    {
      "SEASON_ID": "22004",
      "Player_ID": 2544,
      "Game_ID": "0020400269",
      "GAME_DATE": "Dec 08, 2004",
      "MATCHUP": "CLE @ CHI",
      "WL": "L",
      "MIN": 38,
      "FGM": 5,
      "FGA": 15,
      "FG_PCT": 0.333,
      "FG3M": 0,
      "FG3A": 2,
      "FG3_PCT": 0.0,
      "FTM": 9,
      "FTA": 12,
      "FT_PCT": 0.75,
      "OREB": 0,
      "DREB": 2,
      "REB": 2,
      "AST": 6,
      "STL": 1,
      "BLK": 1,
      "TOV": 4,
      "PF": 2,
      "PTS": 19,
      "PLUS_MINUS": -22,
      "VIDEO_AVAILABLE": 0
    },
    {
      "SEASON_ID": "22004",
      "Player_ID": 2544,
      "Game_ID": "0020400256",
      "GAME_DATE": "Dec 07, 2004",
      "MATCHUP": "CLE vs. NJN",
      "WL": "W",
      "MIN": 46,
      "FGM": 11,
      "FGA": 22,
      "FG_PCT": 0.5,
      "FG3M": 0,
      "FG3A": 1,
      "FG3_PCT": 0.0,
      "FTM": 5,
      "FTA": 6,
      "FT_PCT": 0.833,
      "OREB": 0,
      "DREB": 2,
      "REB": 2,
      "AST": 8,
      "STL": 3,
      "BLK": 0,
      "TOV": 3,
      "PF": 4,
      "PTS": 27,
      "PLUS_MINUS": 6,
      "VIDEO_AVAILABLE": 0
    },
    {
      "SEASON_ID": "22004",
      "Player_ID": 2544,
      "Game_ID": "0020400236",
      "GAME_DATE": "Dec 04, 2004",
      "MATCHUP": "CLE vs. TOR",
      "WL": "W",
      "MIN": 43,
      "FGM": 10,
      "FGA": 17,
      "FG_PCT": 0.588,
      "FG3M": 1,
      "FG3A": 3,
      "FG3_PCT": 0.333,
      "FTM": 6,
      "FTA": 7,
      "FT_PCT": 0.857,
      "OREB": 0,
      "DREB": 6,
      "REB": 6,
      "AST": 10,
      "STL": 2,
      "BLK": 1,
      "TOV": 3,
      "PF": 2,
      "PTS": 27,
      "PLUS_MINUS": 15,
      "VIDEO_AVAILABLE": 0
    },
    {
      "SEASON_ID": "22004",
      "Player_ID": 2544,
      "Game_ID": "0020400223",
      "GAME_DATE": "Dec 02, 2004",
      "MATCHUP": "CLE @ DEN",
      "WL": "W",
      "MIN": 41,
      "FGM": 8,
      "FGA": 17,
      "FG_PCT": 0.471,
      "FG3M": 0,
      "FG3A": 0,
      "FG3_PCT": 0.0,
      "FTM": 1,
      "FTA": 2,
      "FT_PCT": 0.5,
      "OREB": 1,
      "DREB": 7,
      "REB": 8,
      "AST": 9,
      "STL": 2,
      "BLK": 1,
      "TOV": 5,
      "PF": 3,
      "PTS": 17,
      "PLUS_MINUS": 23,
      "VIDEO_AVAILABLE": 0
    },
    {
      "SEASON_ID": "22004",
      "Player_ID": 2544,
      "Game_ID": "0020400218",
      "GAME_DATE": "Dec 01, 2004",
      "MATCHUP": "CLE @ PHO",
      "WL": "L",
      "MIN": 40,
      "FGM": 6,
      "FGA": 19,
      "FG_PCT": 0.316,
      "FG3M": 0,
      "FG3A": 2,
      "FG3_PCT": 0.0,
      "FTM": 3,
      "FTA": 4,
      "FT_PCT": 0.75,
      "OREB": 1,
      "DREB": 2,
      "REB": 3,
      "AST": 6,
      "STL": 2,
      "BLK": 1,
      "TOV": 6,
      "PF": 2,
      "PTS": 15,
      "PLUS_MINUS": -17,
      "VIDEO_AVAILABLE": 0
    },
    {
      "SEASON_ID": "22004",
      "Player_ID": 2544,
      "Game_ID": "0020400201",
      "GAME_DATE": "Nov 29, 2004",
      "MATCHUP": "CLE @ LAC",
      "WL": "L",
      "MIN": 42,
      "FGM": 9,
      "FGA": 19,
      "FG_PCT": 0.474,
      "FG3M": 0,
      "FG3A": 2,
      "FG3_PCT": 0.0,
      "FTM": 4,
      "FTA": 5,
      "FT_PCT": 0.8,
      "OREB": 1,
      "DREB": 6,
      "REB": 7,
      "AST": 5,
      "STL": 6,
      "BLK": 1,
      "TOV": 3,
      "PF": 2,
      "PTS": 22,
      "PLUS_MINUS": -16,
      "VIDEO_AVAILABLE": 0
    },
    {
      "SEASON_ID": "22004",
      "Player_ID": 2544,
      "Game_ID": "0020400187",
      "GAME_DATE": "Nov 27, 2004",
      "MATCHUP": "CLE vs. CHI",
      "WL": "W",
      "MIN": 32,
      "FGM": 11,
      "FGA": 17,
      "FG_PCT": 0.647,
      "FG3M": 1,
      "FG3A": 2,
      "FG3_PCT": 0.5,
      "FTM": 3,
      "FTA": 4,
      "FT_PCT": 0.75,
      "OREB": 1,
      "DREB": 6,
      "REB": 7,
      "AST": 7,
      "STL": 1,
      "BLK": 0,
      "TOV": 2,
      "PF": 0,
      "PTS": 26,
      "PLUS_MINUS": 25,
      "VIDEO_AVAILABLE": 0
    },
    {
      "SEASON_ID": "22004",
      "Player_ID": 2544,
      "Game_ID": "0020400172",
      "GAME_DATE": "Nov 26, 2004",
      "MATCHUP": "CLE @ BOS",
      "WL": "W",
      "MIN": 43,
      "FGM": 9,
      "FGA": 13,
      "FG_PCT": 0.692,
      "FG3M": 0,
      "FG3A": 2,
      "FG3_PCT": 0.0,
      "FTM": 2,
      "FTA": 3,
      "FT_PCT": 0.667,
      "OREB": 0,
      "DREB": 6,
      "REB": 6,
      "AST": 8,
      "STL": 3,
      "BLK": 1,
      "TOV": 2,
      "PF": 2,
      "PTS": 20,
      "PLUS_MINUS": 6,
      "VIDEO_AVAILABLE": 0
    },
    {
      "SEASON_ID": "22004",
      "Player_ID": 2544,
      "Game_ID": "0020400163",
      "GAME_DATE": "Nov 24, 2004",
      "MATCHUP": "CLE vs. DET",
      "WL": "W",
      "MIN": 38,
      "FGM": 15,
      "FGA": 22,
      "FG_PCT": 0.682,
      "FG3M": 2,
      "FG3A": 3,
      "FG3_PCT": 0.667,
      "FTM": 11,
      "FTA": 12,
      "FT_PCT": 0.917,
      "OREB": 3,
      "DREB": 3,
      "REB": 6,
      "AST": 5,
      "STL": 3,
      "BLK": 1,
      "TOV": 3,
      "PF": 3,
      "PTS": 43,
      "PLUS_MINUS": 12,
      "VIDEO_AVAILABLE": 0
    },
    {
      "SEASON_ID": "22004",
      "Player_ID": 2544,
      "Game_ID": "0020400141",
      "GAME_DATE": "Nov 21, 2004",
      "MATCHUP": "CLE @ NYK",
      "WL": "L",
      "MIN": 40,
      "FGM": 5,
      "FGA": 15,
      "FG_PCT": 0.333,
      "FG3M": 1,
      "FG3A": 3,
      "FG3_PCT": 0.333,
      "FTM": 2,
      "FTA": 3,
      "FT_PCT": 0.667,
      "OREB": 2,
      "DREB": 7,
      "REB": 9,
      "AST": 10,
      "STL": 1,
      "BLK": 1,
      "TOV": 5,
      "PF": 3,
      "PTS": 13,
      "PLUS_MINUS": 1,
      "VIDEO_AVAILABLE": 0
    },
    {
      "SEASON_ID": "22004",
      "Player_ID": 2544,
      "Game_ID": "0020400131",
      "GAME_DATE": "Nov 20, 2004",
      "MATCHUP": "CLE vs. CHA",
      "WL": "W",
      "MIN": 38,
      "FGM": 11,
      "FGA": 20,
      "FG_PCT": 0.55,
      "FG3M": 0,
      "FG3A": 2,
      "FG3_PCT": 0.0,
      "FTM": 3,
      "FTA": 4,
      "FT_PCT": 0.75,
      "OREB": 5,
      "DREB": 3,
      "REB": 8,
      "AST": 2,
      "STL": 3,
      "BLK": 1,
      "TOV": 7,
      "PF": 0,
      "PTS": 25,
      "PLUS_MINUS": 24,
      "VIDEO_AVAILABLE": 0
    },
    {
      "SEASON_ID": "22004",
      "Player_ID": 2544,
      "Game_ID": "0020400118",
      "GAME_DATE": "Nov 18, 2004",
      "MATCHUP": "CLE @ CHA",
      "WL": "W",
      "MIN": 30,
      "FGM": 8,
      "FGA": 14,
      "FG_PCT": 0.571,
      "FG3M": 2,
      "FG3A": 3,
      "FG3_PCT": 0.667,
      "FTM": 1,
      "FTA": 2,
      "FT_PCT": 0.5,
      "OREB": 1,
      "DREB": 5,
      "REB": 6,
      "AST": 9,
      "STL": 0,
      "BLK": 0,
      "TOV": 1,
      "PF": 3,
      "PTS": 19,
      "PLUS_MINUS": 21,
      "VIDEO_AVAILABLE": 0
    },
    {
      "SEASON_ID": "22004",
      "Player_ID": 2544,
      "Game_ID": "0020400096",
      "GAME_DATE": "Nov 15, 2004",
      "MATCHUP": "CLE vs. GOS",
      "WL": "W",
      "MIN": 42,
      "FGM": 12,
      "FGA": 22,
      "FG_PCT": 0.545,
      "FG3M": 3,
      "FG3A": 5,
      "FG3_PCT": 0.6,
      "FTM": 6,
      "FTA": 8,
      "FT_PCT": 0.75,
      "OREB": 2,
      "DREB": 10,
      "REB": 12,
      "AST": 4,
      "STL": 2,
      "BLK": 1,
      "TOV": 1,
      "PF": 1,
      "PTS": 33,
      "PLUS_MINUS": 15,
      "VIDEO_AVAILABLE": 0
    },
    {
      "SEASON_ID": "22004",
      "Player_ID": 2544,
      "Game_ID": "0020400081",
      "GAME_DATE": "Nov 13, 2004",
      "MATCHUP": "CLE vs. WAS",
      "WL": "W",
      "MIN": 38,
      "FGM": 10,
      "FGA": 20,
      "FG_PCT": 0.5,
      "FG3M": 0,
      "FG3A": 3,
      "FG3_PCT": 0.0,
      "FTM": 4,
      "FTA": 5,
      "FT_PCT": 0.8,
      "OREB": 1,
      "DREB": 8,
      "REB": 9,
      "AST": 4,
      "STL": 3,
      "BLK": 2,
      "TOV": 4,
      "PF": 0,
      "PTS": 24,
      "PLUS_MINUS": 25,
      "VIDEO_AVAILABLE": 0
    },
    {
      "SEASON_ID": "22004",
      "Player_ID": 2544,
      "Game_ID": "0020400063",
      "GAME_DATE": "Nov 10, 2004",
      "MATCHUP": "CLE vs. PHX",
      "WL": "W",
      "MIN": 48,
      "FGM": 13,
      "FGA": 24,
      "FG_PCT": 0.542,
      "FG3M": 1,
      "FG3A": 2,
      "FG3_PCT": 0.5,
      "FTM": 11,
      "FTA": 12,
      "FT_PCT": 0.917,
      "OREB": 3,
      "DREB": 7,
      "REB": 10,
      "AST": 6,
      "STL": 3,
      "BLK": 3,
      "TOV": 3,
      "PF": 1,
      "PTS": 38,
      "PLUS_MINUS": 14,
      "VIDEO_AVAILABLE": 0
    },
    {
      "SEASON_ID": "22004",
      "Player_ID": 2544,
      "Game_ID": "0020400051",
      "GAME_DATE": "Nov 09, 2004",
      "MATCHUP": "CLE @ ATL",
      "WL": "W",
      "MIN": 48,
      "FGM": 8,
      "FGA": 17,
      "FG_PCT": 0.471,
      "FG3M": 1,
      "FG3A": 4,
      "FG3_PCT": 0.25,
      "FTM": 8,
      "FTA": 12,
      "FT_PCT": 0.667,
      "OREB": 1,
      "DREB": 9,
      "REB": 10,
      "AST": 4,
      "STL": 4,
      "BLK": 2,
      "TOV": 3,
      "PF": 2,
      "PTS": 25,
      "PLUS_MINUS": 14,
      "VIDEO_AVAILABLE": 0
    },
    {
      "SEASON_ID": "22004",
      "Player_ID": 2544,
      "Game_ID": "0020400037",
      "GAME_DATE": "Nov 06, 2004",
      "MATCHUP": "CLE @ MIL",
      "WL": "L",
      "MIN": 42,
      "FGM": 8,
      "FGA": 20,
      "FG_PCT": 0.4,
      "FG3M": 0,
      "FG3A": 3,
      "FG3_PCT": 0.0,
      "FTM": 15,
      "FTA": 22,
      "FT_PCT": 0.682,
      "OREB": 2,
      "DREB": 6,
      "REB": 8,
      "AST": 6,
      "STL": 3,
      "BLK": 0,
      "TOV": 4,
      "PF": 0,
      "PTS": 31,
      "PLUS_MINUS": -12,
      "VIDEO_AVAILABLE": 0
    },
    {
      "SEASON_ID": "22004",
      "Player_ID": 2544,
      "Game_ID": "0020400018",
      "GAME_DATE": "Nov 04, 2004",
      "MATCHUP": "CLE @ MIA",
      "WL": "L",
      "MIN": 43,
      "FGM": 9,
      "FGA": 22,
      "FG_PCT": 0.409,
      "FG3M": 2,
      "FG3A": 3,
      "FG3_PCT": 0.667,
      "FTM": 1,
      "FTA": 1,
      "FT_PCT": 1.0,
      "OREB": 3,
      "DREB": 3,
      "REB": 6,
      "AST": 8,
      "STL": 1,
      "BLK": 0,
      "TOV": 1,
      "PF": 0,
      "PTS": 21,
      "PLUS_MINUS": -8,
      "VIDEO_AVAILABLE": 0
    },
    {
      "SEASON_ID": "22004",
      "Player_ID": 2544,
      "Game_ID": "0020400006",
      "GAME_DATE": "Nov 03, 2004",
      "MATCHUP": "CLE vs. IND",
      "WL": "L",
      "MIN": 50,
      "FGM": 8,
      "FGA": 19,
      "FG_PCT": 0.421,
      "FG3M": 2,
      "FG3A": 5,
      "FG3_PCT": 0.4,
      "FTM": 10,
      "FTA": 12,
      "FT_PCT": 0.833,
      "OREB": 1,
      "DREB": 4,
      "REB": 5,
      "AST": 8,
      "STL": 1,
      "BLK": 3,
      "TOV": 6,
      "PF": 2,
      "PTS": 28,
      "PLUS_MINUS": -10,
      "VIDEO_AVAILABLE": 0
    }
  ],
  "cached_at": "2026-04-20T23:46:55.704314",
  "endpoint": "player_game_log",
  "params": {
    "player_id": 2544,
    "season": "2004-05",
    "season_type": "Regular Season"
  }
}